setup.py
jits/__init__.py
jits/middleware.py
jits/scheduler.py
jits.egg-info/PKG-INFO
jits.egg-info/SOURCES.txt
jits.egg-info/dependency_links.txt
jits.egg-info/requires.txt
jits.egg-info/top_level.txt
jits/app/__init__.py
jits/app/models.py
tests/__init__.py
tests/test_project/__init__.py
tests/test_project/manage.py
tests/test_project/settings.py
tests/test_project/urls.py
tests/test_project/test_app/__init__.py
tests/test_project/test_app/models.py
tests/test_project/test_app/views.py
tests/test_threaded/__init__.py
tests/test_threaded/test_scheduling.py