Metadata-Version: 1.0
Name: jits
Version: 0.1.1
Summary: Django JITS (Just In Time Scheduler)
Home-page: http://jits.pythonesque.org/
Author: Mikeal Rogers
Author-email: mikeal.rogers@gmail.com
License: Python license
Platform: Any
Classifier: Development Status :: 4 - Beta
Classifier: Environment :: Console
Classifier: Intended Audience :: Developers
Classifier: License :: OSI Approved :: Apache Software License
Classifier: Operating System :: OS Independent
Classifier: Topic :: Software Development :: Libraries :: Python Modules
